mflt_build_id/__init__.py
mflt_build_id/py.typed
mflt_build_id-1.1.1.dist-info/licenses/LICENSE
mflt_build_id-1.1.1.dist-info/METADATA
mflt_build_id-1.1.1.dist-info/WHEEL
mflt_build_id-1.1.1.dist-info/entry_points.txt
mflt_build_id-1.1.1.dist-info/top_level.txt
mflt_build_id-1.1.1.dist-info/RECORD
