Metadata-Version: 2.4
Name: mflt-build-id
Version: 1.1.1
Summary: Memfault CLI tool
Author-email: Memfault <hello@memfault.com>
Project-URL: homepage, https://docs.memfault.com
Requires-Python: <4.0,>=3.8
License-File: LICENSE
Requires-Dist: pyelftools>=0.31
Dynamic: license-file
